[{"id":"W19-0100","title":"Proceedings of the Society for Computation in Linguistics ({SC}i{L}) 2019","authors":["Jarosz, Gaja","Nelson, Max","O{'}Connor, Brendan","Pater, Joe"],"emails":["","","",""],"author_id":["gaja-jarosz","max-nelson","brendan-oconnor","joe-pater"],"pages":"i--ii","doi":"10.7275\/ntf6-xx21","url":"https:\/\/www.aclweb.org\/anthology\/W19-0100","year":"2019","booktitle":null},{"id":"W19-0101","title":"Can Entropy Explain Successor Surprisal Effects in Reading?","authors":["van Schijndel, Marten","Linzen, Tal"],"emails":["vansky@jhu.edu","tal.linzen@jhu.edu"],"author_id":["marten-van-schijndel","tal-linzen"],"pages":"1--7","doi":"10.7275\/qtbb-9d05","url":"https:\/\/www.aclweb.org\/anthology\/W19-0101","year":"2019","booktitle":"Proceedings of the Society for Computation in Linguistics ({SC}i{L}) 2019"},{"id":"W19-0102","title":"{R}ed{T}yp: A Database of Reduplication with Computational Models","authors":["Dolatian, Hossep","Heinz, Jeffrey"],"emails":["hossep.dolatian@stonybrook.edu","jeffrey.heinz@stonybrook.edu"],"author_id":["hossep-dolatian","jeffrey-heinz"],"pages":"8--18","doi":"10.7275\/ckx7-s770","url":"https:\/\/www.aclweb.org\/anthology\/W19-0102","year":"2019","booktitle":"Proceedings of the Society for Computation in Linguistics ({SC}i{L}) 2019"},{"id":"W19-0103","title":"Unsupervised Learning of Cross-Lingual Symbol Embeddings Without Parallel Data","authors":["Granroth-Wilding, Mark","Toivonen, Hannu"],"emails":["mark.granroth-wilding@helsinki.fi","hannu.toivonen@cs.helsinki.fi"],"author_id":["mark-granroth-wilding","hannu-toivonen"],"pages":"19--28","doi":"10.7275\/wx64-ea83","url":"https:\/\/www.aclweb.org\/anthology\/W19-0103","year":"2019","booktitle":"Proceedings of the Society for Computation in Linguistics ({SC}i{L}) 2019"},{"id":"W19-0104","title":"Q-Theory Representations are Logically Equivalent to Autosegmental Representations","authors":["Danis, Nick","Jardine, Adam"],"emails":["ndanis@princeton.edu","adam.jardine@rutgers.edu"],"author_id":["nick-danis","adam-jardine"],"pages":"29--38","doi":"10.7275\/tvj1-k306","url":"https:\/\/www.aclweb.org\/anthology\/W19-0104","year":"2019","booktitle":"Proceedings of the Society for Computation in Linguistics ({SC}i{L}) 2019"},{"id":"W19-0105","title":"Modeling Clausal Complementation for a Grammar Engineering Resource","authors":["Zamaraeva, Olga","Howell, Kristen","Bender, Emily M."],"emails":["olzama@uw.edu","kphowell@uw.edu","ebender@uw.edu"],"author_id":["olga-zamaraeva","kristen-howell","emily-m-bender"],"pages":"39--49","doi":"10.7275\/dygn-c796","url":"https:\/\/www.aclweb.org\/anthology\/W19-0105","year":"2019","booktitle":"Proceedings of the Society for Computation in Linguistics ({SC}i{L}) 2019"},{"id":"W19-0106","title":"Do {RNN}s learn human-like abstract word order preferences?","authors":["Futrell, Richard","Levy, Roger P."],"emails":["rfutrell@uci.edu","rplevy@mit.edu"],"author_id":["richard-futrell","roger-levy"],"pages":"50--59","doi":"10.7275\/jb34-9986","url":"https:\/\/www.aclweb.org\/anthology\/W19-0106","year":"2019","booktitle":"Proceedings of the Society for Computation in Linguistics ({SC}i{L}) 2019"},{"id":"W19-0107","title":"Segmentation and {UR} Acquisition with {UR} Constraints","authors":["Nelson, Max"],"emails":["manelson@umass.edu"],"author_id":["max-nelson"],"pages":"60--68","doi":"10.7275\/zc9d-pn56","url":"https:\/\/www.aclweb.org\/anthology\/W19-0107","year":"2019","booktitle":"Proceedings of the Society for Computation in Linguistics ({SC}i{L}) 2019"},{"id":"W19-0108","title":"Constraint breeding during on-line incremental learning","authors":["Moreton, Elliot"],"emails":["moreton@unc.edu"],"author_id":["elliott-moreton"],"pages":"69--80","doi":"10.7275\/6f9x-6411","url":"https:\/\/www.aclweb.org\/anthology\/W19-0108","year":"2019","booktitle":"Proceedings of the Society for Computation in Linguistics ({SC}i{L}) 2019"},{"id":"W19-0109","title":"An Incremental Iterated Response Model of Pragmatics","authors":["Cohn-Gordon, Reuben","Goodman, Noah","Potts, Christopher"],"emails":["reubencg@stanford.edu","ngoodman@stanford.edu","cgpotts@stanford.edu"],"author_id":["reuben-cohn-gordon","noah-goodman","christopher-potts"],"pages":"81--90","doi":"10.7275\/cprc-8x17","url":"https:\/\/www.aclweb.org\/anthology\/W19-0109","year":"2019","booktitle":"Proceedings of the Society for Computation in Linguistics ({SC}i{L}) 2019"},{"id":"W19-0110","title":"Learning Exceptionality and Variation with Lexically Scaled {M}ax{E}nt","authors":["Hughto, Coral","Lamont, Andrew","Prickett, Brandon","Jarosz, Gaja"],"emails":["coralwilliam@linguist.umass.edu","alamont@linguist.umass.edu","bprickett@linguist.umass.edu","jarosz@linguist.umass.edu"],"author_id":["coral-hughto","andrew-lamont","brandon-prickett","gaja-jarosz"],"pages":"91--101","doi":"10.7275\/y68s-kh12","url":"https:\/\/www.aclweb.org\/anthology\/W19-0110","year":"2019","booktitle":"Proceedings of the Society for Computation in Linguistics ({SC}i{L}) 2019"},{"id":"W19-0111","title":"Learning complex inflectional paradigms through blended gradient inputs","authors":["Rosen, Eric R."],"emails":["errosen@mail.ubc.ca"],"author_id":["eric-r-rosen"],"pages":"102--112","doi":"10.7275\/ccwf-j606","url":"https:\/\/www.aclweb.org\/anthology\/W19-0111","year":"2019","booktitle":"Proceedings of the Society for Computation in Linguistics ({SC}i{L}) 2019"},{"id":"W19-0112","title":"Jabberwocky Parsing: Dependency Parsing with Lexical Noise","authors":["Kasai, Jungo","Frank, Robert"],"emails":["jkasai@cs.washington.edu","robert.frank@yale.edu"],"author_id":["jungo-kasai","robert-frank"],"pages":"113--123","doi":"10.7275\/h12q-k754","url":"https:\/\/www.aclweb.org\/anthology\/W19-0112","year":"2019","booktitle":"Proceedings of the Society for Computation in Linguistics ({SC}i{L}) 2019"},{"id":"W19-0113","title":"Learnability and Overgeneration in Computational Syntax","authors":["Hao, Yiding"],"emails":["yiding.hao@yale.edu"],"author_id":["yiding-hao"],"pages":"124--134","doi":"10.7275\/1qmz-bg76","url":"https:\/\/www.aclweb.org\/anthology\/W19-0113","year":"2019","booktitle":"Proceedings of the Society for Computation in Linguistics ({SC}i{L}) 2019"},{"id":"W19-0114","title":"A Conceptual Spaces Model of Socially Motivated Language Change","authors":["Burnett, Heather","Bonami, Olivier"],"emails":["",""],"author_id":["heather-burnett","olivier-bonami"],"pages":"135--145","doi":"10.7275\/5vmp-cs05","url":"https:\/\/www.aclweb.org\/anthology\/W19-0114","year":"2019","booktitle":"Proceedings of the Society for Computation in Linguistics ({SC}i{L}) 2019"},{"id":"W19-0115","title":"Identifying Participation of Individual Verbs or {V}erb{N}et Classes in the Causative Alternation","authors":["Seyffarth, Esther"],"emails":["esther.seyffarth@hhu.de"],"author_id":["esther-seyffarth"],"pages":"146--155","doi":"10.7275\/efvz-jy59","url":"https:\/\/www.aclweb.org\/anthology\/W19-0115","year":"2019","booktitle":"Proceedings of the Society for Computation in Linguistics ({SC}i{L}) 2019"},{"id":"W19-0116","title":"Using Sentiment Induction to Understand Variation in Gendered Online Communities","authors":["Li, Lucy","Mendelsohn, Julia"],"emails":["lucy3@stanford.edu","jmendels@stanford.edu"],"author_id":["lucy-li","julia-mendelsohn"],"pages":"156--166","doi":"10.7275\/11wq-ep51","url":"https:\/\/www.aclweb.org\/anthology\/W19-0116","year":"2019","booktitle":"Proceedings of the Society for Computation in Linguistics ({SC}i{L}) 2019"},{"id":"W19-0117","title":"On the difficulty of a distributional semantics of spoken language","authors":["Chrupa{\\l}a, Grzegorz","Gelderloos, Lieke","K{\\'a}d{\\'a}r, {\\'A}kos","Alishahi, Afra"],"emails":["g.chrupala@uvt.nl","l.j.gelderloos@uvt.nl","a.kadar@uvt.nl","a.alishahi@uvt.nl"],"author_id":["grzegorz-chrupala","lieke-gelderloos","akos-kadar","afra-alishahi"],"pages":"167--173","doi":"10.7275\/extq-7546","url":"https:\/\/www.aclweb.org\/anthology\/W19-0117","year":"2019","booktitle":"Proceedings of the Society for Computation in Linguistics ({SC}i{L}) 2019"},{"id":"W19-0118","title":"Distributional Effects of Gender Contrasts Across Categories","authors":["Mickus, Timothee","Bonami, Olivier","Paperno, Denis"],"emails":["","",""],"author_id":["timothee-mickus","olivier-bonami","denis-paperno"],"pages":"174--184","doi":"10.7275\/g11b-3s25","url":"https:\/\/www.aclweb.org\/anthology\/W19-0118","year":"2019","booktitle":"Proceedings of the Society for Computation in Linguistics ({SC}i{L}) 2019"},{"id":"W19-0119","title":"Guess Who{'}s Coming (and Who{'}s Going): Bringing Perspective to the Rational Speech Acts Framework","authors":["Anderson, Carolyn Jane","Dillon, Brian W."],"emails":["carolynander@umass.edu",""],"author_id":["carolyn-jane-anderson","brian-w-dillon"],"pages":"185--194","doi":"10.7275\/9bn3-8x38","url":"https:\/\/www.aclweb.org\/anthology\/W19-0119","year":"2019","booktitle":"Proceedings of the Society for Computation in Linguistics ({SC}i{L}) 2019"},{"id":"W19-0120","title":"The organization of sound inventories: A study on obstruent gaps","authors":["Wang, Sheng-Fu"],"emails":["shengfu.wang@nyu.edu"],"author_id":["sheng-fu-wang"],"pages":"195--204","doi":"10.7275\/pbe8-zf60","url":"https:\/\/www.aclweb.org\/anthology\/W19-0120","year":"2019","booktitle":"Proceedings of the Society for Computation in Linguistics ({SC}i{L}) 2019"},{"id":"W19-0121","title":"C-Command Dependencies as {TSL} String Constraints","authors":["Graf, Thomas","Shafiei, Nazila"],"emails":["mail@thomasgraf.net","nazila.shafiei@stonybrook.edu"],"author_id":["thomas-graf","nazila-shafiei"],"pages":"205--215","doi":"10.7275\/4rrx-x488","url":"https:\/\/www.aclweb.org\/anthology\/W19-0121","year":"2019","booktitle":"Proceedings of the Society for Computation in Linguistics ({SC}i{L}) 2019"},{"id":"W19-0122","title":"Modeling the Acquisition of Words with Multiple Meanings","authors":["Barak, Libby","Floyd, Sammy","Goldberg, Adele"],"emails":["lbarak@princeton.edu","sfloyd@princeton.edu","adele@princeton.edu"],"author_id":["libby-barak","sammy-floyd","adele-goldberg"],"pages":"216--225","doi":"10.7275\/tr21-m273","url":"https:\/\/www.aclweb.org\/anthology\/W19-0122","year":"2019","booktitle":"Proceedings of the Society for Computation in Linguistics ({SC}i{L}) 2019"},{"id":"W19-0123","title":"Evaluation Order Effects in Dynamic Continuized {CCG}: From Negative Polarity Items to Balanced Punctuation","authors":["White, Michael"],"emails":["mwhite@ling.osu.edu"],"author_id":["michael-white"],"pages":"226--235","doi":"10.7275\/kpch-rk05","url":"https:\/\/www.aclweb.org\/anthology\/W19-0123","year":"2019","booktitle":"Proceedings of the Society for Computation in Linguistics ({SC}i{L}) 2019"},{"id":"W19-0124","title":"Abstract Meaning Representation for Human-Robot Dialogue","authors":["Bonial, Claire N.","Donatelli, Lucia","Ervin, Jessica","Voss, Clare R."],"emails":["claire.n.bonial.civ@mail.mil","","",""],"author_id":["claire-bonial","lucia-donatelli","jessica-ervin","clare-voss"],"pages":"236--246","doi":"10.7275\/v3c5-yd35","url":"https:\/\/www.aclweb.org\/anthology\/W19-0124","year":"2019","booktitle":"Proceedings of the Society for Computation in Linguistics ({SC}i{L}) 2019"},{"id":"W19-0125","title":"A Logical and Computational Methodology for Exploring Systems of Phonotactic Constraints","authors":["Lambert, Dakotah","Rogers, James"],"emails":["djlambe11@earlham.edu","jrogers@cs.earlham.edu"],"author_id":["dakotah-lambert","james-rogers"],"pages":"247--256","doi":"10.7275\/t0dv-9t05","url":"https:\/\/www.aclweb.org\/anthology\/W19-0125","year":"2019","booktitle":"Proceedings of the Society for Computation in Linguistics ({SC}i{L}) 2019"},{"id":"W19-0126","title":"Augmentic Compositional Models for Knowledge Base Completion Using Gradient Representations","authors":["Lalisse, Matthias R.","Smolensky, Paul"],"emails":["lalisse@jhu.edu","smolensky@jhu.edu"],"author_id":["matthias-r-lalisse","paul-smolensky"],"pages":"257--266","doi":"10.7275\/8et8-qd83","url":"https:\/\/www.aclweb.org\/anthology\/W19-0126","year":"2019","booktitle":"Proceedings of the Society for Computation in Linguistics ({SC}i{L}) 2019"},{"id":"W19-0127","title":"Case assignment in {TSL} syntax: a case study","authors":["Vu, Mai Ha","Shafiei, Nazila","Graf, Thomas"],"emails":["maiha@udel.edu","nazila.shafiei@stonybrook.edu","mail@thomasgraf.net"],"author_id":["mai-ha-vu","nazila-shafiei","thomas-graf"],"pages":"267--276","doi":"10.7275\/sywz-xw23","url":"https:\/\/www.aclweb.org\/anthology\/W19-0127","year":"2019","booktitle":"Proceedings of the Society for Computation in Linguistics ({SC}i{L}) 2019"},{"id":"W19-0128","title":"On Evaluating the Generalization of {LSTM} Models in Formal Languages","authors":["Suzgun, Mirac","Belinkov, Yonatan","Shieber, Stuart M."],"emails":["","",""],"author_id":["mirac-suzgun","yonatan-belinkov","stuart-m-shieber"],"pages":"277--286","doi":"10.7275\/s02b-4d91","url":"https:\/\/www.aclweb.org\/anthology\/W19-0128","year":"2019","booktitle":"Proceedings of the Society for Computation in Linguistics ({SC}i{L}) 2019"},{"id":"W19-0129","title":"Verb Argument Structure Alternations in Word and Sentence Embeddings","authors":["Kann, Katharina","Warstadt, Alex","Williams, Adina","Bowman, Samuel R."],"emails":["kann@nyu.edu","warstadt@nyu.edu","adinawilliams@nyu.edu","bowman@nyu.edu"],"author_id":["katharina-kann","alex-warstadt","adina-williams","samuel-bowman"],"pages":"287--297","doi":"10.7275\/q5js-4y86","url":"https:\/\/www.aclweb.org\/anthology\/W19-0129","year":"2019","booktitle":"Proceedings of the Society for Computation in Linguistics ({SC}i{L}) 2019"}]