[{"id":"I11-2001","title":"{W}iki{N}et{TK} {--} A Tool Kit for {E}mbedding{W}orld Knowledge in {NLP} Applications","authors":["Judea, Alex","Nastase, Vivi","Strube, Michael"],"emails":["alexander.judea@h-its.org","vivi.nastase@h-its.org","michael.strube@h-its.org"],"author_id":["alex-judea","vivi-nastase","michael-strube"],"pages":"1--4","url":"https:\/\/www.aclweb.org\/anthology\/I11-2001","publisher":"Asian Federation of Natural Language Processing","address":"Chiang Mai, Thailand","year":"2011","month":"November","booktitle":"Proceedings of the {IJCNLP} 2011 System Demonstrations"},{"id":"I11-2002","title":"Using Linguist{'}s Assistant for Language Description and Translation","authors":["Beale, Stephen"],"emails":["sbeale@cs.umbc.edu"],"author_id":["stephen-beale"],"pages":"5--8","url":"https:\/\/www.aclweb.org\/anthology\/I11-2002","publisher":"Asian Federation of Natural Language Processing","address":"Chiang Mai, Thailand","year":"2011","month":"November","booktitle":"Proceedings of the {IJCNLP} 2011 System Demonstrations"},{"id":"I11-2003","title":"{TTC} {T}erm{S}uite - A {UIMA} Application for Multilingual Terminology Extraction from Comparable Corpora","authors":["Rocheteau, J{\\'e}r{\\^o}me","Daille, B{\\'e}atrice"],"emails":["jerome.rocheteau@univ-nantes.fr","beatrice.daille@univ-nantes.fr"],"author_id":["jerome-rocheteau","beatrice-daille"],"pages":"9--12","url":"https:\/\/www.aclweb.org\/anthology\/I11-2003","publisher":"Asian Federation of Natural Language Processing","address":"Chiang Mai, Thailand","year":"2011","month":"November","booktitle":"Proceedings of the {IJCNLP} 2011 System Demonstrations"}]