[{"id":"W15-2101","title":"Invited Talk: The Case for Universal Dependencies","authors":["Manning, Christopher"],"emails":["manning@cs.stanford.edu"],"author_id":["christopher-d-manning"],"pages":"1","url":"https:\/\/www.aclweb.org\/anthology\/W15-2101","publisher":"Uppsala University, Uppsala, Sweden","address":"Uppsala, Sweden","year":"2015","month":"August","booktitle":"Proceedings of the Third International Conference on Dependency Linguistics (Depling 2015)"},{"id":"W15-2102","title":"Invited Talk: Lexicon Embedded Syntax","authors":["Polgu{\\`e}re, Alain"],"emails":["alain.polguere@univ-lorraine.fr"],"author_id":["alain-polguere"],"pages":"2--9","url":"https:\/\/www.aclweb.org\/anthology\/W15-2102","publisher":"Uppsala University, Uppsala, Sweden","address":"Uppsala, Sweden","year":"2015","month":"August","booktitle":"Proceedings of the Third International Conference on Dependency Linguistics (Depling 2015)"},{"id":"W15-2103","title":"Converting an {E}nglish-{S}wedish Parallel Treebank to Universal Dependencies","authors":["Ahrenberg, Lars"],"emails":["lars.ahrenberg@liu.se"],"author_id":["lars-ahrenberg"],"pages":"10--19","url":"https:\/\/www.aclweb.org\/anthology\/W15-2103","publisher":"Uppsala University, Uppsala, Sweden","address":"Uppsala, Sweden","year":"2015","month":"August","booktitle":"Proceedings of the Third International Conference on Dependency Linguistics (Depling 2015)"},{"id":"W15-2104","title":"Targeted Paraphrasing on Deep Syntactic Layer for {MT} Evaluation","authors":["Baran{\\v{c}}{\\'\\i}kov{\\'a}, Petra","Rosa, Rudolf"],"emails":["barancikova@ufal.mff.cuni.cz","rosa@ufal.mff.cuni.cz"],"author_id":["petra-barancikova","rudolf-rosa"],"pages":"20--27","url":"https:\/\/www.aclweb.org\/anthology\/W15-2104","publisher":"Uppsala University, Uppsala, Sweden","address":"Uppsala, Sweden","year":"2015","month":"August","booktitle":"Proceedings of the Third International Conference on Dependency Linguistics (Depling 2015)"},{"id":"W15-2105","title":"Universal and Language-specific Dependency Relations for Analysing {R}omanian","authors":["Barbu Mititelu, Verginica","M{\\u{a}}r{\\u{a}}nduc, C{\\u{a}}t{\\u{a}}lina","Irimia, Elena"],"emails":["vergi@racai.ro","","elena@racai.ro"],"author_id":["verginica-barbu-mititelu","catalina-maranduc","elena-irimia"],"pages":"28--37","url":"https:\/\/www.aclweb.org\/anthology\/W15-2105","publisher":"Uppsala University, Uppsala, Sweden","address":"Uppsala, Sweden","year":"2015","month":"August","booktitle":"Proceedings of the Third International Conference on Dependency Linguistics (Depling 2015)"},{"id":"W15-2106","title":"Emotion and Inner State Adverbials in {R}ussian","authors":["Boguslavskaya, Olga","Boguslavsky, Igor"],"emails":["lga@gmail.com","oguslavsky@gmail.com"],"author_id":["olga-boguslavskaya","igor-boguslavsky"],"pages":"38--47","url":"https:\/\/www.aclweb.org\/anthology\/W15-2106","publisher":"Uppsala University, Uppsala, Sweden","address":"Uppsala, Sweden","year":"2015","month":"August","booktitle":"Proceedings of the Third International Conference on Dependency Linguistics (Depling 2015)"},{"id":"W15-2107","title":"Towards a multi-layered dependency annotation of {F}innish","authors":["Burga, Alicia","Mille, Simon","Granvik, Anton","Wanner, Leo"],"emails":["alicia.burga@upf.edu","simon.mille@upf.edu","anton.granvik@hanken.fi","leo.wanner@upf.edu"],"author_id":["alicia-burga","simon-mille","anton-granvik","leo-wanner"],"pages":"48--57","url":"https:\/\/www.aclweb.org\/anthology\/W15-2107","publisher":"Uppsala University, Uppsala, Sweden","address":"Uppsala, Sweden","year":"2015","month":"August","booktitle":"Proceedings of the Third International Conference on Dependency Linguistics (Depling 2015)"},{"id":"W15-2108","title":"A {B}ayesian Model for Generative Transition-based Dependency Parsing","authors":["Buys, Jan","Blunsom, Phil"],"emails":["jan.buys@cs.ox.ac.uk","phil.blunsom@cs.ox.ac.uk"],"author_id":["jan-buys","phil-blunsom"],"pages":"58--67","url":"https:\/\/www.aclweb.org\/anthology\/W15-2108","publisher":"Uppsala University, Uppsala, Sweden","address":"Uppsala, Sweden","year":"2015","month":"August","booktitle":"Proceedings of the Third International Conference on Dependency Linguistics (Depling 2015)"},{"id":"W15-2109","title":"On the relation between verb full valency and synonymy","authors":["{\\v{C}}ech, Radek","Ma{\\v{c}}utek, J{\\'a}n","Ko{\\v{s}}{\\v{c}}ov{\\'a}, Michaela"],"emails":["cechradek@gmail.com","jmacutek@yahoo.com","michaela.koscova@fmph.uniba.sk"],"author_id":["radek-cech","jan-macutek","michaela-koscova"],"pages":"68--73","url":"https:\/\/www.aclweb.org\/anthology\/W15-2109","publisher":"Uppsala University, Uppsala, Sweden","address":"Uppsala, Sweden","year":"2015","month":"August","booktitle":"Proceedings of the Third International Conference on Dependency Linguistics (Depling 2015)"},{"id":"W15-2110","title":"Classifying Syntactic Categories in the {C}hinese Dependency Network","authors":["Chen, Xinying","Liu, Haitao","Gerdes, Kim"],"emails":["xy@yuyanxue.net","lhtzju@gmail.com","kim@gerdes.fr"],"author_id":["xinying-chen","haitao-liu","kim-gerdes"],"pages":"74--81","url":"https:\/\/www.aclweb.org\/anthology\/W15-2110","publisher":"Uppsala University, Uppsala, Sweden","address":"Uppsala, Sweden","year":"2015","month":"August","booktitle":"Proceedings of the Third International Conference on Dependency Linguistics (Depling 2015)"},{"id":"W15-2111","title":"Using Parallel Texts and Lexicons for Verbal Word Sense Disambiguation","authors":["Du{\\v{s}}ek, Ond{\\v{r}}ej","Fu{\\v{c}}{\\'\\i}kov{\\'a}, Eva","Haji{\\v{c}}, Jan","Popel, Martin","{\\v{S}}indlerov{\\'a}, Jana","Ure{\\v{s}}ov{\\'a}, Zde{\\v{n}}ka"],"emails":["odusek@ufal.mff.cuni.cz","uresova@ufal.mff.cuni.cz","hajic@ufal.mff.cuni.cz","popel@ufal.mff.cuni.cz","sindlerova@ufal.mff.cuni.cz","fucikova@ufal.mff.cuni.cz"],"author_id":["ondrej-dusek","eva-fucikova","jan-hajic","martin-popel","jana-sindlerova","zdenka-uresova"],"pages":"82--90","url":"https:\/\/www.aclweb.org\/anthology\/W15-2111","publisher":"Uppsala University, Uppsala, Sweden","address":"Uppsala, Sweden","year":"2015","month":"August","booktitle":"Proceedings of the Third International Conference on Dependency Linguistics (Depling 2015)"},{"id":"W15-2112","title":"Quantifying Word Order Freedom in Dependency Corpora","authors":["Futrell, Richard","Mahowald, Kyle","Gibson, Edward"],"emails":["futrell@mit.edu","kylemaho@mit.edu","egibson@mit.edu"],"author_id":["richard-futrell","kyle-mahowald","edward-gibson"],"pages":"91--100","url":"https:\/\/www.aclweb.org\/anthology\/W15-2112","publisher":"Uppsala University, Uppsala, Sweden","address":"Uppsala, Sweden","year":"2015","month":"August","booktitle":"Proceedings of the Third International Conference on Dependency Linguistics (Depling 2015)"},{"id":"W15-2113","title":"Non-constituent coordination and other coordinative constructions as Dependency Graphs","authors":["Gerdes, Kim","Kahane, Sylvain"],"emails":["kim@gerdes.fr","sylvain@kahane.fr"],"author_id":["kim-gerdes","sylvain-kahane"],"pages":"101--110","url":"https:\/\/www.aclweb.org\/anthology\/W15-2113","publisher":"Uppsala University, Uppsala, Sweden","address":"Uppsala, Sweden","year":"2015","month":"August","booktitle":"Proceedings of the Third International Conference on Dependency Linguistics (Depling 2015)"},{"id":"W15-2114","title":"The Dependency Status of Function Words: Auxiliaries","authors":["Gro{\\ss}, Thomas","Osborne, Timothy"],"emails":["tm.gross@yahoo.de","tjo3ya@yahoo.com"],"author_id":["thomas-gross","timothy-osborne"],"pages":"111--120","url":"https:\/\/www.aclweb.org\/anthology\/W15-2114","publisher":"Uppsala University, Uppsala, Sweden","address":"Uppsala, Sweden","year":"2015","month":"August","booktitle":"Proceedings of the Third International Conference on Dependency Linguistics (Depling 2015)"},{"id":"W15-2115","title":"Diachronic Trends in Word Order Freedom and Dependency Length in Dependency-Annotated Corpora of {L}atin and Ancient {G}reek","authors":["Gulordava, Kristina","Merlo, Paola"],"emails":["kristina.gulordava@unige.ch","paola.merlo@unige.ch"],"author_id":["kristina-gulordava","paola-merlo"],"pages":"121--130","url":"https:\/\/www.aclweb.org\/anthology\/W15-2115","publisher":"Uppsala University, Uppsala, Sweden","address":"Uppsala, Sweden","year":"2015","month":"August","booktitle":"Proceedings of the Third International Conference on Dependency Linguistics (Depling 2015)"},{"id":"W15-2116","title":"Reconstructions of Deletions in a Dependency-based Description of {C}zech: Selected Issues","authors":["Haji{\\v{c}}ov{\\'a}, Eva","Mikulov{\\'a}, Marie","Panevov{\\'a}, Jarmila"],"emails":["hajicova@ufal.mff.cuni.cz","mikulova@ufal.mff.cuni.cz","panevova@ufal.mff.cuni.cz"],"author_id":["eva-hajicova","marie-mikulova","jarmila-panevova"],"pages":"131--140","url":"https:\/\/www.aclweb.org\/anthology\/W15-2116","publisher":"Uppsala University, Uppsala, Sweden","address":"Uppsala, Sweden","year":"2015","month":"August","booktitle":"Proceedings of the Third International Conference on Dependency Linguistics (Depling 2015)"},{"id":"W15-2117","title":"Non-projectivity and processing constraints: Insights from {H}indi","authors":["Husain, Samar","Vasishth, Shravan"],"emails":["samar@hss.iitd.ac.in","vasishth@uni-potsdam.de"],"author_id":["samar-husain","shravan-vasishth"],"pages":"141--150","url":"https:\/\/www.aclweb.org\/anthology\/W15-2117","publisher":"Uppsala University, Uppsala, Sweden","address":"Uppsala, Sweden","year":"2015","month":"August","booktitle":"Proceedings of the Third International Conference on Dependency Linguistics (Depling 2015)"},{"id":"W15-2118","title":"From mutual dependency to multiple dimensions: remarks on the {DG} analysis of {``}functional heads{''} in {H}ungarian","authors":["Imr{\\'e}nyi, Andr{\\'a}s"],"emails":["imrenyi.andras@gmail.com"],"author_id":["andras-imrenyi"],"pages":"151--160","url":"https:\/\/www.aclweb.org\/anthology\/W15-2118","publisher":"Uppsala University, Uppsala, Sweden","address":"Uppsala, Sweden","year":"2015","month":"August","booktitle":"Proceedings of the Third International Conference on Dependency Linguistics (Depling 2015)"},{"id":"W15-2119","title":"Mean Hierarchical Distance Augmenting Mean Dependency Distance","authors":["Jing, Yingqi","Liu, Haitao"],"emails":["jakenevergivesup@gmail.com","htliu@163.com"],"author_id":["yingqi-jing","haitao-liu"],"pages":"161--170","url":"https:\/\/www.aclweb.org\/anthology\/W15-2119","publisher":"Uppsala University, Uppsala, Sweden","address":"Uppsala, Sweden","year":"2015","month":"August","booktitle":"Proceedings of the Third International Conference on Dependency Linguistics (Depling 2015)"},{"id":"W15-2120","title":"Towards Cross-language Application of Dependency Grammar","authors":["J{\\\"a}rvinen, Timo","Bertol, Elisabeth","Larasati, Septina","Rizea, Monica-Mihaela","Ruiz Santabalbina, Maria","Sou{\\v{c}}ek, Milan"],"emails":["timo.jarvinen@lionbridge.com","liz.bertol@gmail.com","septina.larasati@gmail.com","monicamihaelarizea@gmail.com","mrsantabalbina@gmail.com","milan.soucek@lionbridge.com"],"author_id":["timo-jarvinen","elisabeth-bertol","septina-dian-larasati","monica-mihaela-rizea","maria-ruiz-santabalbina","milan-soucek"],"pages":"171--180","url":"https:\/\/www.aclweb.org\/anthology\/W15-2120","publisher":"Uppsala University, Uppsala, Sweden","address":"Uppsala, Sweden","year":"2015","month":"August","booktitle":"Proceedings of the Third International Conference on Dependency Linguistics (Depling 2015)"},{"id":"W15-2121","title":"Dependency-based analyses for function words {--} Introducing the polygraphic approach","authors":["Kahane, Sylvain","Mazziotta, Nicolas"],"emails":["sylvain@kahane.fr","nicolas.mazziotta@ulg.ac.be"],"author_id":["sylvain-kahane","nicolas-mazziotta"],"pages":"181--190","url":"https:\/\/www.aclweb.org\/anthology\/W15-2121","publisher":"Uppsala University, Uppsala, Sweden","address":"Uppsala, Sweden","year":"2015","month":"August","booktitle":"Proceedings of the Third International Conference on Dependency Linguistics (Depling 2015)"},{"id":"W15-2122","title":"At the Lexicon-Grammar Interface: The Case of Complex Predicates in the Functional Generative Description","authors":["Kettnerov{\\'a}, V{\\'a}clava","Lopatkov{\\'a}, Mark{\\'e}ta"],"emails":["kettnerova@ufal.mff.cuni.cz","lopatkova@ufal.mff.cuni.cz"],"author_id":["vaclava-kettnerova","marketa-lopatkova"],"pages":"191--200","url":"https:\/\/www.aclweb.org\/anthology\/W15-2122","publisher":"Uppsala University, Uppsala, Sweden","address":"Uppsala, Sweden","year":"2015","month":"August","booktitle":"Proceedings of the Third International Conference on Dependency Linguistics (Depling 2015)"},{"id":"W15-2123","title":"Enhancing {F}ree{L}ing Rule-Based Dependency Grammars with Subcategorization Frames","authors":["Lloberes, Marina","Castell{\\'o}n, Irene","Padr{\\'o}, Llu{\\'\\i}s"],"emails":["mllobesa8@alumnes.ub.edu","icastellon@ub.edu","padro@cs.upc.edu"],"author_id":["marina-lloberes","irene-castellon","lluis-padro"],"pages":"201--210","url":"https:\/\/www.aclweb.org\/anthology\/W15-2123","publisher":"Uppsala University, Uppsala, Sweden","address":"Uppsala, Sweden","year":"2015","month":"August","booktitle":"Proceedings of the Third International Conference on Dependency Linguistics (Depling 2015)"},{"id":"W15-2124","title":"Towards Universal Web Parsebanks","authors":["Luotolahti, Juhani","Kanerva, Jenna","Laippala, Veronika","Pyysalo, Sampo","Ginter, Filip"],"emails":["juhani.luotolahti@utu.fi","jenna.kanerva@utu.fi","veronika.laippala@utu.fi","sampo.pyysalo@utu.fi","filip.ginter@utu.fi"],"author_id":["juhani-luotolahti","jenna-kanerva","veronika-laippala","sampo-pyysalo","filip-ginter"],"pages":"211--220","url":"https:\/\/www.aclweb.org\/anthology\/W15-2124","publisher":"Uppsala University, Uppsala, Sweden","address":"Uppsala, Sweden","year":"2015","month":"August","booktitle":"Proceedings of the Third International Conference on Dependency Linguistics (Depling 2015)"},{"id":"W15-2125","title":"Evaluation of Two-level Dependency Representations of Argument Structure in Long-Distance Dependencies","authors":["Merlo, Paola"],"emails":["erlo@unige.ch"],"author_id":["paola-merlo"],"pages":"221--230","url":"https:\/\/www.aclweb.org\/anthology\/W15-2125","publisher":"Uppsala University, Uppsala, Sweden","address":"Uppsala, Sweden","year":"2015","month":"August","booktitle":"Proceedings of the Third International Conference on Dependency Linguistics (Depling 2015)"},{"id":"W15-2126","title":"The Subjectival Surface-Syntactic Relation in {S}erbian","authors":["Mili{\\'c}evi{\\'c}, Jasmina"],"emails":["jmilicev@dal.ca"],"author_id":["jasmina-milicevic"],"pages":"231--240","url":"https:\/\/www.aclweb.org\/anthology\/W15-2126","publisher":"Uppsala University, Uppsala, Sweden","address":"Uppsala, Sweden","year":"2015","month":"August","booktitle":"Proceedings of the Third International Conference on Dependency Linguistics (Depling 2015)"},{"id":"W15-2127","title":"A Historical Overview of the Status of Function Words in Dependency Grammar","authors":["Osborne, Timothy","Maxwell, Daniel"],"emails":["tjo3ya@yahoo.com","dan.maxwell@gmail.com"],"author_id":["timothy-osborne","daniel-maxwell"],"pages":"241--250","url":"https:\/\/www.aclweb.org\/anthology\/W15-2127","publisher":"Uppsala University, Uppsala, Sweden","address":"Uppsala, Sweden","year":"2015","month":"August","booktitle":"Proceedings of the Third International Conference on Dependency Linguistics (Depling 2015)"},{"id":"W15-2128","title":"Diagnostics for Constituents: Dependency, Constituency, and the Status of Function Words","authors":["Osborne, Timothy"],"emails":["tjo3ya@yahoo.com"],"author_id":["timothy-osborne"],"pages":"251--260","url":"https:\/\/www.aclweb.org\/anthology\/W15-2128","publisher":"Uppsala University, Uppsala, Sweden","address":"Uppsala, Sweden","year":"2015","month":"August","booktitle":"Proceedings of the Third International Conference on Dependency Linguistics (Depling 2015)"},{"id":"W15-2129","title":"A {DG} Account of the Descriptive and Resultative de-Constructions in {C}hinese","authors":["Osborne, Timothy","Ma, Shudong"],"emails":["tjo3ya@yahoo.com","shudong.ma@qq.com"],"author_id":["timothy-osborne","shudong-ma"],"pages":"261--270","url":"https:\/\/www.aclweb.org\/anthology\/W15-2129","publisher":"Uppsala University, Uppsala, Sweden","address":"Uppsala, Sweden","year":"2015","month":"August","booktitle":"Proceedings of the Third International Conference on Dependency Linguistics (Depling 2015)"},{"id":"W15-2130","title":"A Survey of Ellipsis in {C}hinese","authors":["Osborne, Timothy","Liang, Junying"],"emails":["tjo3ya@yahoo.com","jyleung@iipc.zju.edu"],"author_id":["timothy-osborne","junying-liang"],"pages":"271--280","url":"https:\/\/www.aclweb.org\/anthology\/W15-2130","publisher":"Uppsala University, Uppsala, Sweden","address":"Uppsala, Sweden","year":"2015","month":"August","booktitle":"Proceedings of the Third International Conference on Dependency Linguistics (Depling 2015)"},{"id":"W15-2131","title":"Multi-source Cross-lingual Delexicalized Parser Transfer: {P}rague or {S}tanford?","authors":["Rosa, Rudolf"],"emails":["rosa@ufal.mff.cuni.cz"],"author_id":["rudolf-rosa"],"pages":"281--290","url":"https:\/\/www.aclweb.org\/anthology\/W15-2131","publisher":"Uppsala University, Uppsala, Sweden","address":"Uppsala, Sweden","year":"2015","month":"August","booktitle":"Proceedings of the Third International Conference on Dependency Linguistics (Depling 2015)"},{"id":"W15-2132","title":"Secondary Connectives in the {P}rague Dependency Treebank","authors":["Rysov{\\'a}, Magdal{\\'e}na","Rysov{\\'a}, Kate{\\v{r}}ina"],"emails":["magdalena.rysova@post.cz","katerina.rysova@post.cz"],"author_id":["magdalena-rysova","katerina-rysova"],"pages":"291--299","url":"https:\/\/www.aclweb.org\/anthology\/W15-2132","publisher":"Uppsala University, Uppsala, Sweden","address":"Uppsala, Sweden","year":"2015","month":"August","booktitle":"Proceedings of the Third International Conference on Dependency Linguistics (Depling 2015)"},{"id":"W15-2133","title":"{P}ars{P}er: A Dependency Parser for {P}ersian","authors":["Seraji, Mojgan","Bohnet, Bernd","Nivre, Joakim"],"emails":["mojgan.seraji@lingfil.uu.se","bohnetbd@gmail.com","joakim.nivre@lingfil.uu.se"],"author_id":["mojgan-seraji","bernd-bohnet","joakim-nivre"],"pages":"300--309","url":"https:\/\/www.aclweb.org\/anthology\/W15-2133","publisher":"Uppsala University, Uppsala, Sweden","address":"Uppsala, Sweden","year":"2015","month":"August","booktitle":"Proceedings of the Third International Conference on Dependency Linguistics (Depling 2015)"},{"id":"W15-2134","title":"Does Universal Dependencies need a parsing representation? An investigation of {E}nglish","authors":["Silveira, Natalia","Manning, Christopher"],"emails":["natalias@stanford.edu","manning@stanford.edu"],"author_id":["natalia-silveira","christopher-d-manning"],"pages":"310--319","url":"https:\/\/www.aclweb.org\/anthology\/W15-2134","publisher":"Uppsala University, Uppsala, Sweden","address":"Uppsala, Sweden","year":"2015","month":"August","booktitle":"Proceedings of the Third International Conference on Dependency Linguistics (Depling 2015)"},{"id":"W15-2135","title":"Catena Operations for Unified Dependency Analysis","authors":["Simov, Kiril","Osenova, Petya"],"emails":["kivs@bultreebank.org","petya@bultreebank.org"],"author_id":["kiril-simov","petya-osenova"],"pages":"320--329","url":"https:\/\/www.aclweb.org\/anthology\/W15-2135","publisher":"Uppsala University, Uppsala, Sweden","address":"Uppsala, Sweden","year":"2015","month":"August","booktitle":"Proceedings of the Third International Conference on Dependency Linguistics (Depling 2015)"},{"id":"W15-2136","title":"Zero Alignment of Verb Arguments in a Parallel Treebank","authors":["{\\v{S}}indlerov{\\'a}, Jana","Fu{\\v{c}}{\\'\\i}kov{\\'a}, Eva","Ure{\\v{s}}ov{\\'a}, Zde{\\v{n}}ka"],"emails":["sindlerova@ufal.mff.cuni.cz","uresova@ufal.mff.cuni.cz","fucikova@ufal.mff.cuni.cz"],"author_id":["jana-sindlerova","eva-fucikova","zdenka-uresova"],"pages":"330--339","url":"https:\/\/www.aclweb.org\/anthology\/W15-2136","publisher":"Uppsala University, Uppsala, Sweden","address":"Uppsala, Sweden","year":"2015","month":"August","booktitle":"Proceedings of the Third International Conference on Dependency Linguistics (Depling 2015)"},{"id":"W15-2137","title":"Cross-Lingual Dependency Parsing with Universal Dependencies and Predicted {P}o{S} Labels","authors":["Tiedemann, J{\\\"o}rg"],"emails":["j{\\\"o}rg.tiedemann@lingfil.uu.se"],"author_id":["jorg-tiedemann"],"pages":"340--349","url":"https:\/\/www.aclweb.org\/anthology\/W15-2137","publisher":"Uppsala University, Uppsala, Sweden","address":"Uppsala, Sweden","year":"2015","month":"August","booktitle":"Proceedings of the Third International Conference on Dependency Linguistics (Depling 2015)"},{"id":"W15-2138","title":"Exploring Confidence-based Self-training for Multilingual Dependency Parsing in an Under-Resourced Language Scenario","authors":["Yu, Juntao","Bohnet, Bernd"],"emails":["j.yu.1@cs.bham.ac.uk","bohnetbd@google.com"],"author_id":["juntao-yu","bernd-bohnet"],"pages":"350--358","url":"https:\/\/www.aclweb.org\/anthology\/W15-2138","publisher":"Uppsala University, Uppsala, Sweden","address":"Uppsala, Sweden","year":"2015","month":"August","booktitle":"Proceedings of the Third International Conference on Dependency Linguistics (Depling 2015)"}]