[{"id":"W17-3501","title":"Linguistic realisation as machine translation: Comparing different {MT} models for {AMR}-to-text generation","authors":["Castro Ferreira, Thiago","Calixto, Iacer","Wubben, Sander","Krahmer, Emiel"],"emails":["tcastrof@tilburguniversity.edu","iacer.calixto@adaptcentre.ie","s.wubben@tilburguniversity.edu","e.j.krahmer@tilburguniversity.edu"],"author_id":["thiago-castro-ferreira","iacer-calixto","sander-wubben","emiel-krahmer"],"pages":"1--10","doi":"10.18653\/v1\/W17-3501","url":"https:\/\/www.aclweb.org\/anthology\/W17-3501","publisher":"Association for Computational Linguistics","address":"Santiago de Compostela, Spain","year":"2017","month":"September","booktitle":"Proceedings of the 10th International Conference on Natural Language Generation"},{"id":"W17-3502","title":"A Survey on Intelligent Poetry Generation: Languages, Features, Techniques, Reutilisation and Evaluation","authors":["Gon{\\c{c}}alo Oliveira, Hugo"],"emails":["hroliv@dei.uc.pt"],"author_id":["hugo-goncalo-oliveira"],"pages":"11--20","doi":"10.18653\/v1\/W17-3502","url":"https:\/\/www.aclweb.org\/anthology\/W17-3502","publisher":"Association for Computational Linguistics","address":"Santiago de Compostela, Spain","year":"2017","month":"September","booktitle":"Proceedings of the 10th International Conference on Natural Language Generation"},{"id":"W17-3503","title":"Cross-linguistic differences and similarities in image descriptions","authors":["van Miltenburg, Emiel","Elliott, Desmond","Vossen, Piek"],"emails":["emiel.van.miltenburg@vu.nl","d.elliott@ed.ac.uk","piek.vossen@vu.nl"],"author_id":["emiel-van-miltenburg","desmond-elliott","piek-vossen"],"pages":"21--30","doi":"10.18653\/v1\/W17-3503","url":"https:\/\/www.aclweb.org\/anthology\/W17-3503","publisher":"Association for Computational Linguistics","address":"Santiago de Compostela, Spain","year":"2017","month":"September","booktitle":"Proceedings of the 10th International Conference on Natural Language Generation"},{"id":"W17-3504","title":"Content Selection for Real-time Sports News Construction from Commentary Texts","authors":["Yao, Jin-ge","Zhang, Jianmin","Wan, Xiaojun","Xiao, Jianguo"],"emails":["yaojinge@pku.edu.cn","zhangjianmin2015@pku.edu.cn","wanxiaojun@pku.edu.cn","xiaojianguo@pku.edu.cn"],"author_id":["jin-ge-yao","jianmin-zhang","xiaojun-wan","jianguo-xiao"],"pages":"31--40","doi":"10.18653\/v1\/W17-3504","url":"https:\/\/www.aclweb.org\/anthology\/W17-3504","publisher":"Association for Computational Linguistics","address":"Santiago de Compostela, Spain","year":"2017","month":"September","booktitle":"Proceedings of the 10th International Conference on Natural Language Generation"},{"id":"W17-3505","title":"Improving the Naturalness and Expressivity of Language Generation for {S}panish","authors":["Barros, Cristina","Gkatzia, Dimitra","Lloret, Elena"],"emails":["cbarros@dlsi.ua.es","d.gkatzia@napier.ac.uk","elloret@dlsi.ua.es"],"author_id":["cristina-barros","dimitra-gkatzia","elena-lloret"],"pages":"41--50","doi":"10.18653\/v1\/W17-3505","url":"https:\/\/www.aclweb.org\/anthology\/W17-3505","publisher":"Association for Computational Linguistics","address":"Santiago de Compostela, Spain","year":"2017","month":"September","booktitle":"Proceedings of the 10th International Conference on Natural Language Generation"},{"id":"W17-3506","title":"What is the Role of Recurrent Neural Networks ({RNN}s) in an Image Caption Generator?","authors":["Tanti, Marc","Gatt, Albert","Camilleri, Kenneth"],"emails":["marc.tanti.06@um.edu.mt","albert.gatt@um.edu.mt","kenneth.camilleri@um.edu.mt"],"author_id":["marc-tanti","albert-gatt","kenneth-camilleri"],"pages":"51--60","doi":"10.18653\/v1\/W17-3506","url":"https:\/\/www.aclweb.org\/anthology\/W17-3506","publisher":"Association for Computational Linguistics","address":"Santiago de Compostela, Spain","year":"2017","month":"September","booktitle":"Proceedings of the 10th International Conference on Natural Language Generation"},{"id":"W17-3507","title":"Exploring the Behavior of Classic {REG} Algorithms in the Description of Characters in 3{D} Images","authors":["M{\\'e}ndez, Gonzalo","Herv{\\'a}s, Raquel","Bautista, Susana","Rabad{\\'a}n, Adri{\\'a}n","Rodr{\\'\\i}guez, Teresa"],"emails":["gmendez@fdi.ucm.es","raquelhb@fdi.ucm.es","subautis@fdi.ucm.es","arabadan@ucm.es","teresaro@ucm.es"],"author_id":["gonzalo-mendez","raquel-hervas","susana-bautista","adrian-rabadan","teresa-rodriguez"],"pages":"61--69","doi":"10.18653\/v1\/W17-3507","url":"https:\/\/www.aclweb.org\/anthology\/W17-3507","publisher":"Association for Computational Linguistics","address":"Santiago de Compostela, Spain","year":"2017","month":"September","booktitle":"Proceedings of the 10th International Conference on Natural Language Generation"},{"id":"W17-3508","title":"Co-{P}oe{T}ry{M}e: a Co-Creative Interface for the Composition of Poetry","authors":["Gon{\\c{c}}alo Oliveira, Hugo","Mendes, Tiago","Boavida, Ana"],"emails":["hroliv@dei.uc.pt","tjmendes@student.dei.uc.pt","aboavida@dei.uc.pt"],"author_id":["hugo-goncalo-oliveira","tiago-mendes","ana-boavida"],"pages":"70--71","doi":"10.18653\/v1\/W17-3508","url":"https:\/\/www.aclweb.org\/anthology\/W17-3508","publisher":"Association for Computational Linguistics","address":"Santiago de Compostela, Spain","year":"2017","month":"September","booktitle":"Proceedings of the 10th International Conference on Natural Language Generation"},{"id":"W17-3509","title":"Refer-i{TTS}: A System for Referring in Spoken Installments to Objects in Real-World Images","authors":["Zarrie{\\ss}, Sina","L{\\'o}pez Gambino, M. Soledad","Schlangen, David"],"emails":["sina.zarriess@uni-bielefeld.de","","david.schlangen@uni-bielefeld.de"],"author_id":["sina-zarriess","m-soledad-lopez-gambino","david-schlangen"],"pages":"72--73","doi":"10.18653\/v1\/W17-3509","url":"https:\/\/www.aclweb.org\/anthology\/W17-3509","publisher":"Association for Computational Linguistics","address":"Santiago de Compostela, Spain","year":"2017","month":"September","booktitle":"Proceedings of the 10th International Conference on Natural Language Generation"},{"id":"W17-3510","title":"Finding the {``}right{''} answers for customers","authors":["Schilder, Frank"],"emails":[""],"author_id":["frank-schilder"],"pages":"74","doi":"10.18653\/v1\/W17-3510","url":"https:\/\/www.aclweb.org\/anthology\/W17-3510","publisher":"Association for Computational Linguistics","address":"Santiago de Compostela, Spain","year":"2017","month":"September","booktitle":"Proceedings of the 10th International Conference on Natural Language Generation"},{"id":"W17-3511","title":"Referring Expression Generation under Uncertainty: Algorithm and Evaluation Framework","authors":["Williams, Tom","Scheutz, Matthias"],"emails":["williams@cs.tufts.edu","matthias.scheutz@tufts.edu"],"author_id":["tom-williams","matthias-scheutz"],"pages":"75--84","doi":"10.18653\/v1\/W17-3511","url":"https:\/\/www.aclweb.org\/anthology\/W17-3511","publisher":"Association for Computational Linguistics","address":"Santiago de Compostela, Spain","year":"2017","month":"September","booktitle":"Proceedings of the 10th International Conference on Natural Language Generation"},{"id":"W17-3512","title":"Natural Language Descriptions for Human Activities in Video Streams","authors":["Alharbi, Nouf","Gotoh, Yoshihiko"],"emails":["nmalharbi1@sheffield.ac.uk","y.gotoh@sheffield.ac.uk"],"author_id":["nouf-alharbi","yoshihiko-gotoh"],"pages":"85--94","doi":"10.18653\/v1\/W17-3512","url":"https:\/\/www.aclweb.org\/anthology\/W17-3512","publisher":"Association for Computational Linguistics","address":"Santiago de Compostela, Spain","year":"2017","month":"September","booktitle":"Proceedings of the 10th International Conference on Natural Language Generation"},{"id":"W17-3513","title":"{PASS}: A {D}utch data-to-text system for soccer, targeted towards specific audiences","authors":["van der Lee, Chris","Krahmer, Emiel","Wubben, Sander"],"emails":["c.vdrlee@tilburguniversity.edu","e.j.krahmer@tilburguniversity.edu","s.wubben@tilburguniversity.edu"],"author_id":["chris-van-der-lee","emiel-krahmer","sander-wubben"],"pages":"95--104","doi":"10.18653\/v1\/W17-3513","url":"https:\/\/www.aclweb.org\/anthology\/W17-3513","publisher":"Association for Computational Linguistics","address":"Santiago de Compostela, Spain","year":"2017","month":"September","booktitle":"Proceedings of the 10th International Conference on Natural Language Generation"},{"id":"W17-3514","title":"Evaluation of a {R}unyankore grammar engine for healthcare messages","authors":["Byamugisha, Joan","Keet, C. Maria","DeRenzi, Brian"],"emails":["jbyamugisha@cs.uct.ac.za","mkeet@cs.uct.ac.za","bderenzi@cs.uct.ac.za"],"author_id":["joan-byamugisha","c-maria-keet","brian-derenzi"],"pages":"105--113","doi":"10.18653\/v1\/W17-3514","url":"https:\/\/www.aclweb.org\/anthology\/W17-3514","publisher":"Association for Computational Linguistics","address":"Santiago de Compostela, Spain","year":"2017","month":"September","booktitle":"Proceedings of the 10th International Conference on Natural Language Generation"},{"id":"W17-3515","title":"Talking about the world with a distributed model","authors":["Boleda, Gemma"],"emails":[""],"author_id":["gemma-boleda"],"pages":"114","doi":"10.18653\/v1\/W17-3515","url":"https:\/\/www.aclweb.org\/anthology\/W17-3515","publisher":"Association for Computational Linguistics","address":"Santiago de Compostela, Spain","year":"2017","month":"September","booktitle":"Proceedings of the 10th International Conference on Natural Language Generation"},{"id":"W17-3516","title":"The {C}ode2{T}ext Challenge: Text Generation in Source Libraries","authors":["Richardson, Kyle","Zarrie{\\ss}, Sina","Kuhn, Jonas"],"emails":["kyle@ims.uni-stuttgart.de","sina.zarriess@uni-bielefeld.de",""],"author_id":["kyle-richardson","sina-zarriess","jonas-kuhn"],"pages":"115--119","doi":"10.18653\/v1\/W17-3516","url":"https:\/\/www.aclweb.org\/anthology\/W17-3516","publisher":"Association for Computational Linguistics","address":"Santiago de Compostela, Spain","year":"2017","month":"September","booktitle":"Proceedings of the 10th International Conference on Natural Language Generation"},{"id":"W17-3517","title":"Shared Task Proposal: Multilingual Surface Realization Using Universal Dependency Trees","authors":["Mille, Simon","Bohnet, Bernd","Wanner, Leo","Belz, Anja"],"emails":["simon.mille@upf.edu","bohnetbd@google.com","leo.wanner@upf.edu","elz@brighton.ac.uk"],"author_id":["simon-mille","bernd-bohnet","leo-wanner","anja-belz"],"pages":"120--123","doi":"10.18653\/v1\/W17-3517","url":"https:\/\/www.aclweb.org\/anthology\/W17-3517","publisher":"Association for Computational Linguistics","address":"Santiago de Compostela, Spain","year":"2017","month":"September","booktitle":"Proceedings of the 10th International Conference on Natural Language Generation"},{"id":"W17-3518","title":"The {W}eb{NLG} Challenge: Generating Text from {RDF} Data","authors":["Gardent, Claire","Shimorina, Anastasia","Narayan, Shashi","Perez-Beltrachini, Laura"],"emails":["claire.gardent@loria.fr","anastasia.shimorina@loria.fr","shashi.narayan@ed.ac.uk","lperez@ed.ac.uk"],"author_id":["claire-gardent","anastasia-shimorina","shashi-narayan","laura-perez-beltrachini"],"pages":"124--133","doi":"10.18653\/v1\/W17-3518","url":"https:\/\/www.aclweb.org\/anthology\/W17-3518","publisher":"Association for Computational Linguistics","address":"Santiago de Compostela, Spain","year":"2017","month":"September","booktitle":"Proceedings of the 10th International Conference on Natural Language Generation"},{"id":"W17-3519","title":"A Commercial Perspective on Reference","authors":["Reiter, Ehud"],"emails":["ehud.reiter@arria.com"],"author_id":["ehud-reiter"],"pages":"134--138","doi":"10.18653\/v1\/W17-3519","url":"https:\/\/www.aclweb.org\/anthology\/W17-3519","publisher":"Association for Computational Linguistics","address":"Santiago de Compostela, Spain","year":"2017","month":"September","booktitle":"Proceedings of the 10th International Conference on Natural Language Generation"},{"id":"W17-3520","title":"Integrated sentence generation using charts","authors":["Koller, Alexander","Engonopoulos, Nikos"],"emails":["koller@coli.uni-saarland.de","nikos@coli.uni-saarland.de"],"author_id":["alexander-koller","nikos-engonopoulos"],"pages":"139--143","doi":"10.18653\/v1\/W17-3520","url":"https:\/\/www.aclweb.org\/anthology\/W17-3520","publisher":"Association for Computational Linguistics","address":"Santiago de Compostela, Spain","year":"2017","month":"September","booktitle":"Proceedings of the 10th International Conference on Natural Language Generation"},{"id":"W17-3521","title":"Adapting {S}imple{NLG} to {S}panish","authors":["Ramos-Soto, Alejandro","Janeiro-Gallardo, Julio","Bugar{\\'\\i}n Diz, Alberto"],"emails":["alejandro.ramos@usc.es","julio.janeiro@usc.es","alberto.bugarin.diz@usc.es"],"author_id":["alejandro-ramos-soto","julio-janeiro-gallardo","alberto-bugarin-diz"],"pages":"144--148","doi":"10.18653\/v1\/W17-3521","url":"https:\/\/www.aclweb.org\/anthology\/W17-3521","publisher":"Association for Computational Linguistics","address":"Santiago de Compostela, Spain","year":"2017","month":"September","booktitle":"Proceedings of the 10th International Conference on Natural Language Generation"},{"id":"W17-3522","title":"G-{TUNA}: a corpus of referring expressions in {G}erman, including duration information","authors":["Howcroft, David","Vogels, Jorrig","Demberg, Vera"],"emails":["howcroft@coli.uni-saarland.de","jorrig@coli.uni-saarland.de","vera@coli.uni-saarland.de"],"author_id":["david-m-howcroft","jorrig-vogels","vera-demberg"],"pages":"149--153","doi":"10.18653\/v1\/W17-3522","url":"https:\/\/www.aclweb.org\/anthology\/W17-3522","publisher":"Association for Computational Linguistics","address":"Santiago de Compostela, Spain","year":"2017","month":"September","booktitle":"Proceedings of the 10th International Conference on Natural Language Generation"},{"id":"W17-3523","title":"Toward an {NLG} System for {B}antu languages: first steps with {R}unyankore (demo)","authors":["Byamugisha, Joan","Keet, C. Maria","DeRenzi, Brian"],"emails":["jbyamugisha@cs.uct.ac.za","mkeet@cs.uct.ac.za","bderenzi@cs.uct.ac.za"],"author_id":["joan-byamugisha","c-maria-keet","brian-derenzi"],"pages":"154--155","doi":"10.18653\/v1\/W17-3523","url":"https:\/\/www.aclweb.org\/anthology\/W17-3523","publisher":"Association for Computational Linguistics","address":"Santiago de Compostela, Spain","year":"2017","month":"September","booktitle":"Proceedings of the 10th International Conference on Natural Language Generation"},{"id":"W17-3524","title":"A working, non-trivial, topically indifferent {NLG} System for 17 languages","authors":["Wei{\\ss}graeber, Robert","Madsack, Andreas"],"emails":["robert.weissgraeber@ax-semantics.com","andreas.madsack@ax-semantics.com"],"author_id":["robert-weissgraeber","andreas-madsack"],"pages":"156--157","doi":"10.18653\/v1\/W17-3524","url":"https:\/\/www.aclweb.org\/anthology\/W17-3524","publisher":"Association for Computational Linguistics","address":"Santiago de Compostela, Spain","year":"2017","month":"September","booktitle":"Proceedings of the 10th International Conference on Natural Language Generation"},{"id":"W17-3525","title":"Generating titles for millions of browse pages on an e-Commerce site","authors":["Mathur, Prashant","Ueffing, Nicola","Leusch, Gregor"],"emails":["","",""],"author_id":["prashant-mathur","nicola-ueffing","gregor-leusch"],"pages":"158--167","doi":"10.18653\/v1\/W17-3525","url":"https:\/\/www.aclweb.org\/anthology\/W17-3525","publisher":"Association for Computational Linguistics","address":"Santiago de Compostela, Spain","year":"2017","month":"September","booktitle":"Proceedings of the 10th International Conference on Natural Language Generation"},{"id":"W17-3526","title":"Towards Automatic Generation of Product Reviews from Aspect-Sentiment Scores","authors":["Zang, Hongyu","Wan, Xiaojun"],"emails":["zanghy@pku.edu.cn","wanxiaojun@pku.edu.cn"],"author_id":["hongyu-zang","xiaojun-wan"],"pages":"168--177","doi":"10.18653\/v1\/W17-3526","url":"https:\/\/www.aclweb.org\/anthology\/W17-3526","publisher":"Association for Computational Linguistics","address":"Santiago de Compostela, Spain","year":"2017","month":"September","booktitle":"Proceedings of the 10th International Conference on Natural Language Generation"},{"id":"W17-3527","title":"A model of suspense for narrative generation","authors":["Doust, Richard","Piwek, Paul"],"emails":["richard.doust@gmail.com","paul.piwek@open.ac.uk"],"author_id":["richard-doust","paul-piwek"],"pages":"178--187","doi":"10.18653\/v1\/W17-3527","url":"https:\/\/www.aclweb.org\/anthology\/W17-3527","publisher":"Association for Computational Linguistics","address":"Santiago de Compostela, Spain","year":"2017","month":"September","booktitle":"Proceedings of the 10th International Conference on Natural Language Generation"},{"id":"W17-3528","title":"Data-Driven News Generation for Automated Journalism","authors":["Lepp{\\\"a}nen, Leo","Munezero, Myriam","Granroth-Wilding, Mark","Toivonen, Hannu"],"emails":["","","",""],"author_id":["leo-leppanen","myriam-munezero","mark-granroth-wilding","hannu-toivonen"],"pages":"188--197","doi":"10.18653\/v1\/W17-3528","url":"https:\/\/www.aclweb.org\/anthology\/W17-3528","publisher":"Association for Computational Linguistics","address":"Santiago de Compostela, Spain","year":"2017","month":"September","booktitle":"Proceedings of the 10th International Conference on Natural Language Generation"},{"id":"W17-3529","title":"Data Augmentation for Visual Question Answering","authors":["Kafle, Kushal","Yousefhussien, Mohammed","Kanan, Christopher"],"emails":["kk6055@rit.edu","mxy7332@rit.edu","kanan@rit.edu"],"author_id":["kushal-kafle","mohammed-yousefhussien","christopher-kanan"],"pages":"198--202","doi":"10.18653\/v1\/W17-3529","url":"https:\/\/www.aclweb.org\/anthology\/W17-3529","publisher":"Association for Computational Linguistics","address":"Santiago de Compostela, Spain","year":"2017","month":"September","booktitle":"Proceedings of the 10th International Conference on Natural Language Generation"},{"id":"W17-3530","title":"Personalized Questions, Answers and Grammars: Aiding the Search for Relevant Web Information","authors":["Gatius, Marta"],"emails":["gatius@cs.upc.edu"],"author_id":["marta-gatius"],"pages":"203--207","doi":"10.18653\/v1\/W17-3530","url":"https:\/\/www.aclweb.org\/anthology\/W17-3530","publisher":"Association for Computational Linguistics","address":"Santiago de Compostela, Spain","year":"2017","month":"September","booktitle":"Proceedings of the 10th International Conference on Natural Language Generation"},{"id":"W17-3531","title":"A Comparison of Neural Models for Word Ordering","authors":["Hasler, Eva","Stahlberg, Felix","Tomalin, Marcus","de Gispert, Adri{\\`a}","Byrne, Bill"],"emails":["ehasler@sdl.com","fs439@cam.ac.uk","mt126@cam.ac.uk","agispert@sdl.com","bbyrne@sdl.com"],"author_id":["eva-hasler","felix-stahlberg","marcus-tomalin","adria-de-gispert","bill-byrne"],"pages":"208--212","doi":"10.18653\/v1\/W17-3531","url":"https:\/\/www.aclweb.org\/anthology\/W17-3531","publisher":"Association for Computational Linguistics","address":"Santiago de Compostela, Spain","year":"2017","month":"September","booktitle":"Proceedings of the 10th International Conference on Natural Language Generation"},{"id":"W17-3532","title":"Investigating the content and form of referring expressions in {M}andarin: introducing the Mtuna corpus","authors":["van Deemter, Kees","Sun, Le","Sybesma, Rint","Li, Xiao","Chen, Bo","Yang, Muyun"],"emails":["","","","","",""],"author_id":["kees-van-deemter","le-sun","rint-sybesma","xiao-li","bo-chen","muyun-yang"],"pages":"213--217","doi":"10.18653\/v1\/W17-3532","url":"https:\/\/www.aclweb.org\/anthology\/W17-3532","publisher":"Association for Computational Linguistics","address":"Santiago de Compostela, Spain","year":"2017","month":"September","booktitle":"Proceedings of the 10th International Conference on Natural Language Generation"},{"id":"W17-3533","title":"Realization of long sentences using chunking","authors":["Muszy{\\'n}ska, Ewa","Copestake, Ann"],"emails":["emm68@cam.ac.uk","aac10@cam.ac.uk"],"author_id":["ewa-muszynska","ann-copestake"],"pages":"218--222","doi":"10.18653\/v1\/W17-3533","url":"https:\/\/www.aclweb.org\/anthology\/W17-3533","publisher":"Association for Computational Linguistics","address":"Santiago de Compostela, Spain","year":"2017","month":"September","booktitle":"Proceedings of the 10th International Conference on Natural Language Generation"},{"id":"W17-3534","title":"{S}a{T}o{S}: Assessing and Summarising Terms of Services from {G}erman Webshops","authors":["Braun, Daniel","Scepankova, Elena","Holl, Patrick","Matthes, Florian"],"emails":["daniel.braun@tum.de","elena.scepankova@tum.de","patrick.holl@tum.de","matthes@tum.de"],"author_id":["daniel-braun","elena-scepankova","patrick-holl","florian-matthes"],"pages":"223--227","doi":"10.18653\/v1\/W17-3534","url":"https:\/\/www.aclweb.org\/anthology\/W17-3534","publisher":"Association for Computational Linguistics","address":"Santiago de Compostela, Spain","year":"2017","month":"September","booktitle":"Proceedings of the 10th International Conference on Natural Language Generation"},{"id":"W17-3535","title":"Textually Summarising Incomplete Data","authors":["Inglis, Stephanie","Reiter, Ehud","Sripada, Somayajulu"],"emails":["r01si14@abdn.ac.uk","e.reiter@abdn.ac.uk","yaji.sripada@abdn.ac.uk"],"author_id":["stephanie-inglis","ehud-reiter","somayajulu-sripada"],"pages":"228--232","doi":"10.18653\/v1\/W17-3535","url":"https:\/\/www.aclweb.org\/anthology\/W17-3535","publisher":"Association for Computational Linguistics","address":"Santiago de Compostela, Spain","year":"2017","month":"September","booktitle":"Proceedings of the 10th International Conference on Natural Language Generation"},{"id":"W17-3536","title":"Improving the generation of personalised descriptions","authors":["Castro Ferreira, Thiago","Paraboni, Ivandr{\\'e}"],"emails":["tcastrof@tilburguniversity.edu","ivandre@usp.br"],"author_id":["thiago-castro-ferreira","ivandre-paraboni"],"pages":"233--237","doi":"10.18653\/v1\/W17-3536","url":"https:\/\/www.aclweb.org\/anthology\/W17-3536","publisher":"Association for Computational Linguistics","address":"Santiago de Compostela, Spain","year":"2017","month":"September","booktitle":"Proceedings of the 10th International Conference on Natural Language Generation"},{"id":"W17-3537","title":"Analysing Data-To-Text Generation Benchmarks","authors":["Perez-Beltrachini, Laura","Gardent, Claire"],"emails":["",""],"author_id":["laura-perez-beltrachini","claire-gardent"],"pages":"238--242","doi":"10.18653\/v1\/W17-3537","url":"https:\/\/www.aclweb.org\/anthology\/W17-3537","publisher":"Association for Computational Linguistics","address":"Santiago de Compostela, Spain","year":"2017","month":"September","booktitle":"Proceedings of the 10th International Conference on Natural Language Generation"},{"id":"W17-3538","title":"Linguistic Description of Complex Phenomena with the r{LDCP} R Package","authors":["Alonso, Jose","Conde-Clemente, Patricia","Trivino, Gracian"],"emails":["josemaria.alonso.moral@usc.es","",""],"author_id":["jose-m-alonso","patricia-conde-clemente","gracian-trivino"],"pages":"243--244","doi":"10.18653\/v1\/W17-3538","url":"https:\/\/www.aclweb.org\/anthology\/W17-3538","publisher":"Association for Computational Linguistics","address":"Santiago de Compostela, Spain","year":"2017","month":"September","booktitle":"Proceedings of the 10th International Conference on Natural Language Generation"},{"id":"W17-3539","title":"A demo of {FORG}e: the {P}ompeu {F}abra Open Rule-based Generator","authors":["Mille, Simon","Wanner, Leo"],"emails":["simon.mille@upf.edu","leo.wanner@upf.edu"],"author_id":["simon-mille","leo-wanner"],"pages":"245--246","doi":"10.18653\/v1\/W17-3539","url":"https:\/\/www.aclweb.org\/anthology\/W17-3539","publisher":"Association for Computational Linguistics","address":"Santiago de Compostela, Spain","year":"2017","month":"September","booktitle":"Proceedings of the 10th International Conference on Natural Language Generation"},{"id":"W17-3540","title":"Referential Success of Set Referring Expressions with Fuzzy Properties","authors":["Mar{\\'\\i}n, Nicol{\\'a}s","Rivas-Gervilla, Gustavo","S{\\'a}nchez, Daniel"],"emails":["nicm@decsai.ugr.es","",""],"author_id":["nicolas-marin","gustavo-rivas-gervilla","daniel-sanchez-cisneros"],"pages":"247--251","doi":"10.18653\/v1\/W17-3540","url":"https:\/\/www.aclweb.org\/anthology\/W17-3540","publisher":"Association for Computational Linguistics","address":"Santiago de Compostela, Spain","year":"2017","month":"September","booktitle":"Proceedings of the 10th International Conference on Natural Language Generation"},{"id":"W17-3541","title":"Neural Response Generation for Customer Service based on Personality Traits","authors":["Herzig, Jonathan","Shmueli-Scheuer, Michal","Sandbank, Tommy","Konopnicki, David"],"emails":["hjon@il.ibm.com","shmueli@il.ibm.com","tommy@il.ibm.com","davidko@il.ibm.com"],"author_id":["jonathan-herzig","michal-shmueli-scheuer","tommy-sandbank","david-konopnicki"],"pages":"252--256","doi":"10.18653\/v1\/W17-3541","url":"https:\/\/www.aclweb.org\/anthology\/W17-3541","publisher":"Association for Computational Linguistics","address":"Santiago de Compostela, Spain","year":"2017","month":"September","booktitle":"Proceedings of the 10th International Conference on Natural Language Generation"},{"id":"W17-3542","title":"Neural Paraphrase Generation using Transfer Learning","authors":["Brad, Florin","Rebedea, Traian"],"emails":["fbrad@bitdefender.com","traian.rebedea@cs.pub.ro"],"author_id":["florin-brad","traian-rebedea"],"pages":"257--261","doi":"10.18653\/v1\/W17-3542","url":"https:\/\/www.aclweb.org\/anthology\/W17-3542","publisher":"Association for Computational Linguistics","address":"Santiago de Compostela, Spain","year":"2017","month":"September","booktitle":"Proceedings of the 10th International Conference on Natural Language Generation"}]