[{"id":"W18-0901","title":"Challenges in Finding Metaphorical Connections","authors":["Gero, Katy","Chilton, Lydia"],"emails":["katy@cs.columbia.edu","chilton@cs.columbia.edu"],"author_id":["katy-gero","lydia-chilton"],"pages":"1--6","doi":"10.18653\/v1\/W18-0901","url":"https:\/\/www.aclweb.org\/anthology\/W18-0901","publisher":"Association for Computational Linguistics","address":"New Orleans, Louisiana","year":"2018","month":"June","booktitle":"Proceedings of the Workshop on Figurative Language Processing"},{"id":"W18-0902","title":"Linguistic Features of Sarcasm and Metaphor Production Quality","authors":["Skalicky, Stephen","Crossley, Scott"],"emails":["scskalicky@gmail.com","scrossley@gsu.edu"],"author_id":["stephen-skalicky","scott-crossley"],"pages":"7--16","doi":"10.18653\/v1\/W18-0902","url":"https:\/\/www.aclweb.org\/anthology\/W18-0902","publisher":"Association for Computational Linguistics","address":"New Orleans, Louisiana","year":"2018","month":"June","booktitle":"Proceedings of the Workshop on Figurative Language Processing"},{"id":"W18-0903","title":"Leveraging Syntactic Constructions for Metaphor Identification","authors":["Stowe, Kevin","Palmer, Martha"],"emails":["kevin.stowe@colorado.edu","martha.palmer@colorado.edu"],"author_id":["kevin-stowe","martha-palmer"],"pages":"17--26","doi":"10.18653\/v1\/W18-0903","url":"https:\/\/www.aclweb.org\/anthology\/W18-0903","publisher":"Association for Computational Linguistics","address":"New Orleans, Louisiana","year":"2018","month":"June","booktitle":"Proceedings of the Workshop on Figurative Language Processing"},{"id":"W18-0904","title":"Literal, Metphorical or Both? Detecting Metaphoricity in Isolated Adjective-Noun Phrases","authors":["Mykowiecka, Agnieszka","Marciniak, Malgorzata","Wawer, Aleksander"],"emails":["agn@ipipan.waw.pl","mm@ipipan.waw.pl","axw@ipipan.waw.pl"],"author_id":["agnieszka-mykowiecka","malgorzata-marciniak","aleksander-wawer"],"pages":"27--33","doi":"10.18653\/v1\/W18-0904","url":"https:\/\/www.aclweb.org\/anthology\/W18-0904","publisher":"Association for Computational Linguistics","address":"New Orleans, Louisiana","year":"2018","month":"June","booktitle":"Proceedings of the Workshop on Figurative Language Processing"},{"id":"W18-0905","title":"Catching Idiomatic Expressions in {EFL} Essays","authors":["Flor, Michael","Beigman Klebanov, Beata"],"emails":["mflor@ets.org","bbeigmanklebanov@ets.org"],"author_id":["michael-flor","beata-beigman-klebanov"],"pages":"34--44","doi":"10.18653\/v1\/W18-0905","url":"https:\/\/www.aclweb.org\/anthology\/W18-0905","publisher":"Association for Computational Linguistics","address":"New Orleans, Louisiana","year":"2018","month":"June","booktitle":"Proceedings of the Workshop on Figurative Language Processing"},{"id":"W18-0906","title":"Predicting Human Metaphor Paraphrase Judgments with Deep Neural Networks","authors":["Bizzoni, Yuri","Lappin, Shalom"],"emails":["yuri.bizzoni@gu.se","shalom.lappin@gu.se"],"author_id":["yuri-bizzoni","shalom-lappin"],"pages":"45--55","doi":"10.18653\/v1\/W18-0906","url":"https:\/\/www.aclweb.org\/anthology\/W18-0906","publisher":"Association for Computational Linguistics","address":"New Orleans, Louisiana","year":"2018","month":"June","booktitle":"Proceedings of the Workshop on Figurative Language Processing"},{"id":"W18-0907","title":"A Report on the 2018 {VUA} Metaphor Detection Shared Task","authors":["Leong, Chee Wee (Ben)","Beigman Klebanov, Beata","Shutova, Ekaterina"],"emails":["cleong@ets.org","bbeigmanklebanov@ets.org","e.shutova@uva.nl"],"author_id":["chee-wee-leong","beata-beigman-klebanov","ekaterina-shutova"],"pages":"56--66","doi":"10.18653\/v1\/W18-0907","url":"https:\/\/www.aclweb.org\/anthology\/W18-0907","publisher":"Association for Computational Linguistics","address":"New Orleans, Louisiana","year":"2018","month":"June","booktitle":"Proceedings of the Workshop on Figurative Language Processing"},{"id":"W18-0908","title":"An {LSTM}-{CRF} Based Approach to Token-Level Metaphor Detection","authors":["Pramanick, Malay","Gupta, Ashim","Mitra, Pabitra"],"emails":["malay.pramanick@iitkgp.ac.in","ashimgupta95@gmail.com","pabitra@cse.iitkgp.ernet.in"],"author_id":["malay-pramanick","ashim-gupta","pabitra-mitra"],"pages":"67--75","doi":"10.18653\/v1\/W18-0908","url":"https:\/\/www.aclweb.org\/anthology\/W18-0908","publisher":"Association for Computational Linguistics","address":"New Orleans, Louisiana","year":"2018","month":"June","booktitle":"Proceedings of the Workshop on Figurative Language Processing"},{"id":"W18-0909","title":"Unsupervised Detection of Metaphorical Adjective-Noun Pairs","authors":["Pramanick, Malay","Mitra, Pabitra"],"emails":["malay.pramanick@iitkgp.ac.in","pabitra@cse.iitkgp.ernet.in"],"author_id":["malay-pramanick","pabitra-mitra"],"pages":"76--80","doi":"10.18653\/v1\/W18-0909","url":"https:\/\/www.aclweb.org\/anthology\/W18-0909","publisher":"Association for Computational Linguistics","address":"New Orleans, Louisiana","year":"2018","month":"June","booktitle":"Proceedings of the Workshop on Figurative Language Processing"},{"id":"W18-0910","title":"Phrase-Level Metaphor Identification Using Distributed Representations of Word Meaning","authors":["Zayed, Omnia","McCrae, John Philip","Buitelaar, Paul"],"emails":["omnia.zayed@insight-centre.org","john.mccrae@insight-centre.org","paul.buitelaar@insight-centre.org"],"author_id":["omnia-zayed","john-philip-mccrae","paul-buitelaar"],"pages":"81--90","doi":"10.18653\/v1\/W18-0910","url":"https:\/\/www.aclweb.org\/anthology\/W18-0910","publisher":"Association for Computational Linguistics","address":"New Orleans, Louisiana","year":"2018","month":"June","booktitle":"Proceedings of the Workshop on Figurative Language Processing"},{"id":"W18-0911","title":"Bigrams and {B}i{LSTM}s Two Neural Networks for Sequential Metaphor Detection","authors":["Bizzoni, Yuri","Ghanimifard, Mehdi"],"emails":["yuri.bizzoni@gu.se","mehdi.ghanimifard@gu.se"],"author_id":["yuri-bizzoni","mehdi-ghanimifard"],"pages":"91--101","doi":"10.18653\/v1\/W18-0911","url":"https:\/\/www.aclweb.org\/anthology\/W18-0911","publisher":"Association for Computational Linguistics","address":"New Orleans, Louisiana","year":"2018","month":"June","booktitle":"Proceedings of the Workshop on Figurative Language Processing"},{"id":"W18-0912","title":"Computationally Constructed Concepts: A Machine Learning Approach to Metaphor Interpretation Using Usage-Based Construction Grammatical Cues","authors":["Rosen, Zachary"],"emails":[""],"author_id":["zachary-rosen"],"pages":"102--109","doi":"10.18653\/v1\/W18-0912","url":"https:\/\/www.aclweb.org\/anthology\/W18-0912","publisher":"Association for Computational Linguistics","address":"New Orleans, Louisiana","year":"2018","month":"June","booktitle":"Proceedings of the Workshop on Figurative Language Processing"},{"id":"W18-0913","title":"Neural Metaphor Detecting with {CNN}-{LSTM} Model","authors":["Wu, Chuhan","Wu, Fangzhao","Chen, Yubo","Wu, Sixing","Yuan, Zhigang","Huang, Yongfeng"],"emails":["wuch15@mails.tsinghua.edu.cn","wufangzhao@gmail.com","ybch14@mails.tsinghua.edu.cn","wu-sx15@mails.tsinghua.edu.cn","yuanzg14@mails.tsinghua.edu.cn","yfhuang@mails.tsinghua.edu.cn"],"author_id":["chuhan-wu","fangzhao-wu","yubo-chen","sixing-wu","zhigang-yuan","yongfeng-huang"],"pages":"110--114","doi":"10.18653\/v1\/W18-0913","url":"https:\/\/www.aclweb.org\/anthology\/W18-0913","publisher":"Association for Computational Linguistics","address":"New Orleans, Louisiana","year":"2018","month":"June","booktitle":"Proceedings of the Workshop on Figurative Language Processing"},{"id":"W18-0914","title":"Di-{LSTM} Contrast : A Deep Neural Network for Metaphor Detection","authors":["Swarnkar, Krishnkant","Singh, Anil Kumar"],"emails":["krishnkant.swarnkar.cse15@iitbhu.ac.in","aksingh.cse@iitbhu.ac.in"],"author_id":["krishnkant-swarnkar","anil-kumar-singh"],"pages":"115--120","doi":"10.18653\/v1\/W18-0914","url":"https:\/\/www.aclweb.org\/anthology\/W18-0914","publisher":"Association for Computational Linguistics","address":"New Orleans, Louisiana","year":"2018","month":"June","booktitle":"Proceedings of the Workshop on Figurative Language Processing"},{"id":"W18-0915","title":"Conditional Random Fields for Metaphor Detection","authors":["Mosolova, Anna","Bondarenko, Ivan","Fomin, Vadim"],"emails":["1a.mosolova@g.nsu.ru","i.yu.bondarenko@gmail.com","3wadimiusz@gmail.com"],"author_id":["anna-mosolova","ivan-bondarenko","vadim-fomin"],"pages":"121--123","doi":"10.18653\/v1\/W18-0915","url":"https:\/\/www.aclweb.org\/anthology\/W18-0915","publisher":"Association for Computational Linguistics","address":"New Orleans, Louisiana","year":"2018","month":"June","booktitle":"Proceedings of the Workshop on Figurative Language Processing"},{"id":"W18-0916","title":"Detecting Figurative Word Occurrences Using Recurrent Neural Networks","authors":["Mykowiecka, Agnieszka","Wawer, Aleksander","Marciniak, Malgorzata"],"emails":["agn@ipipan.waw.pl","axw@ipipan.waw.pl","mm@ipipan.waw.pl"],"author_id":["agnieszka-mykowiecka","aleksander-wawer","malgorzata-marciniak"],"pages":"124--127","doi":"10.18653\/v1\/W18-0916","url":"https:\/\/www.aclweb.org\/anthology\/W18-0916","publisher":"Association for Computational Linguistics","address":"New Orleans, Louisiana","year":"2018","month":"June","booktitle":"Proceedings of the Workshop on Figurative Language Processing"},{"id":"W18-0917","title":"Multi-Module Recurrent Neural Networks with Transfer Learning","authors":["Skurniak, Filip","Janicka, Maria","Wawer, Aleksander"],"emails":["f.skurniak@samsung.com","m.janicka@samsung.com","a.wawer@samsung.com"],"author_id":["filip-skurniak","maria-janicka","aleksander-wawer"],"pages":"128--132","doi":"10.18653\/v1\/W18-0917","url":"https:\/\/www.aclweb.org\/anthology\/W18-0917","publisher":"Association for Computational Linguistics","address":"New Orleans, Louisiana","year":"2018","month":"June","booktitle":"Proceedings of the Workshop on Figurative Language Processing"},{"id":"W18-0918","title":"Using Language Learner Data for Metaphor Detection","authors":["Stemle, Egon","Onysko, Alexander"],"emails":["egon.stemle@eurac.edu","alexander.onysko@aau.at"],"author_id":["egon-stemle","alexander-onysko"],"pages":"133--138","doi":"10.18653\/v1\/W18-0918","url":"https:\/\/www.aclweb.org\/anthology\/W18-0918","publisher":"Association for Computational Linguistics","address":"New Orleans, Louisiana","year":"2018","month":"June","booktitle":"Proceedings of the Workshop on Figurative Language Processing"}]