[{"id":"W19-6801","title":"Finite State Transducer based Morphology analysis for {M}alayalam Language","authors":["Thottingal, Santhosh"],"emails":["santhosh.thottingal@gmail.com"],"author_id":["santhosh-thottingal"],"pages":"1--5","url":"https:\/\/www.aclweb.org\/anthology\/W19-6801","publisher":"European Association for Machine Translation","address":"Dublin, Ireland","year":"2019","month":"August","booktitle":"Proceedings of the 2nd Workshop on Technologies for MT of Low Resource Languages"},{"id":"W19-6802","title":"A step towards Torwali machine translation: an analysis of morphosyntactic challenges in a low-resource language","authors":["Uddin, Naeem","Uddin, Jalal"],"emails":["naeemuddinhadi@gmail.com","torwalipk@gmail.com"],"author_id":["naeem-uddin","jalal-uddin"],"pages":"6--10","url":"https:\/\/www.aclweb.org\/anthology\/W19-6802","publisher":"European Association for Machine Translation","address":"Dublin, Ireland","year":"2019","month":"August","booktitle":"Proceedings of the 2nd Workshop on Technologies for MT of Low Resource Languages"},{"id":"W19-6803","title":"Workflows for kickstarting {RBMT} in virtually No-Resource Situation","authors":["Pirinen, Tommi A"],"emails":["tommi.antero.pirinen@uni-hamburg.de"],"author_id":["tommi-a-pirinen"],"pages":"11--16","url":"https:\/\/www.aclweb.org\/anthology\/W19-6803","publisher":"European Association for Machine Translation","address":"Dublin, Ireland","year":"2019","month":"August","booktitle":"Proceedings of the 2nd Workshop on Technologies for MT of Low Resource Languages"},{"id":"W19-6804","title":"A Continuous Improvement Framework of Machine Translation for {S}hipibo-Konibo","authors":["Montoya, H{\\'e}ctor Erasmo G{\\'o}mez","Rojas, Kervy Dante Rivas","Oncevay, Arturo"],"emails":["hector.gomez@pucp.pe","k.rivas@pucp.pe","a.oncevay@ed.ac.uk"],"author_id":["hector-erasmo-gomez-montoya","kervy-dante-rivas-rojas","arturo-oncevay"],"pages":"17--23","url":"https:\/\/www.aclweb.org\/anthology\/W19-6804","publisher":"European Association for Machine Translation","address":"Dublin, Ireland","year":"2019","month":"August","booktitle":"Proceedings of the 2nd Workshop on Technologies for MT of Low Resource Languages"},{"id":"W19-6805","title":"Machine Translation for Crimean {T}atar to {T}urkish","authors":["G{\\\"o}k{\\i}rmak, Memduh","Tyers, Francis","Washington, Jonathan"],"emails":["memduhg@gmail.com","ftyers@iu.edu","jonathan.washington@swarthmore.edu"],"author_id":["memduh-gokirmak","francis-tyers","jonathan-washington"],"pages":"24--31","url":"https:\/\/www.aclweb.org\/anthology\/W19-6805","publisher":"European Association for Machine Translation","address":"Dublin, Ireland","year":"2019","month":"August","booktitle":"Proceedings of the 2nd Workshop on Technologies for MT of Low Resource Languages"},{"id":"W19-6806","title":"Developing a Neural Machine Translation system for Irish","authors":["Defauw, Arne","Szoc, Sara","Vanallemeersch, Tom","Bardadym, Anna","Brabers, Joris","Everaert, Frederic","Scholte, Kim","Winckel, Koen Van","den Bogaert, Joachim Van"],"emails":["arne.defauw@crosslang.com","sara.szoc@crosslang.com","tom.vanallemeersch@crosslang.com","anna.bardadym@crosslang.com","joris.brabers@crosslang.com","frederic.everaert@crosslang.com","kim.scholte@crosslang.com","koen.winckel@crosslang.com","joachim.den bogaert@crosslang.com"],"author_id":["arne-defauw","sara-szoc","tom-vanallemeersch","anna-bardadym","joris-brabers","frederic-everaert","kim-scholte","koen-van-winckel","joachim-van-den-bogaert"],"pages":"32--38","url":"https:\/\/www.aclweb.org\/anthology\/W19-6806","publisher":"European Association for Machine Translation","address":"Dublin, Ireland","year":"2019","month":"August","booktitle":"Proceedings of the 2nd Workshop on Technologies for MT of Low Resource Languages"},{"id":"W19-6807","title":"Sentence-Level Adaptation for Low-Resource Neural Machine Translation","authors":["Mueller, Aaron","Lal, Yash Kumar"],"emails":["amueller@jhu.edu","ykumar@jhu.edu"],"author_id":["aaron-mueller","yash-kumar-lal"],"pages":"39--47","url":"https:\/\/www.aclweb.org\/anthology\/W19-6807","publisher":"European Association for Machine Translation","address":"Dublin, Ireland","year":"2019","month":"August","booktitle":"Proceedings of the 2nd Workshop on Technologies for MT of Low Resource Languages"},{"id":"W19-6808","title":"Corpus Building for Low Resource Languages in the {DARPA} {LORELEI} Program","authors":["Tracey, Jennifer","Strassel, Stephanie","Bies, Ann","Song, Zhiyi","Arrigo, Michael","Griffitt, Kira","Delgado, Dana","Graff, Dave","Kulick, Seth","Mott, Justin","Kuster, Neil"],"emails":["garjen@ldc.upenn.edu","strassel@ldc.upenn.edu","bies@ldc.upenn.edu","zhiyi@ldc.upenn.edu","marrigo@ldc.upenn.edu","kiragrif@ldc.upenn.edu","danafore@ldc.upenn.edu","graff@ldc.upenn.edu","kulick@ldc.upenn.edu","jmott@ldc.upenn.edu","neilkus@ldc.upenn.edu"],"author_id":["jennifer-tracey","stephanie-strassel","ann-bies","zhiyi-song","michael-arrigo","kira-griffitt","dana-delgado","dave-graff","seth-kulick","justin-mott","neil-kuster"],"pages":"48--55","url":"https:\/\/www.aclweb.org\/anthology\/W19-6808","publisher":"European Association for Machine Translation","address":"Dublin, Ireland","year":"2019","month":"August","booktitle":"Proceedings of the 2nd Workshop on Technologies for MT of Low Resource Languages"},{"id":"W19-6809","title":"Multilingual Multimodal Machine Translation for {D}ravidian Languages utilizing Phonetic Transcription","authors":["Chakravarthi, Bharathi Raja","Priyadharshini, Ruba","Stearns, Bernardo","Jayapal, Arun","S, Sridevy","Arcan, Mihael","Zarrouk, Manel","McCrae, John P"],"emails":["bharathi.chakravarthi@insight-centre.org","ruba.priyadharshini@insight-centre.org","bernardo.stearns@insight-centre.org","arun.jayapal@insight-centre.org","sridevy.s@insight-centre.org","mihael.arcan@insight-centre.org","manel.zarrouk@insight-centre.org","john.mccrae@insight-centre.org"],"author_id":["bharathi-raja-chakravarthi","ruba-priyadharshini","bernardo-stearns","arun-kumar-jayapal","sridevy-s","mihael-arcan","manel-zarrouk","john-p-mccrae"],"pages":"56--63","url":"https:\/\/www.aclweb.org\/anthology\/W19-6809","publisher":"European Association for Machine Translation","address":"Dublin, Ireland","year":"2019","month":"August","booktitle":"Proceedings of the 2nd Workshop on Technologies for MT of Low Resource Languages"},{"id":"W19-6810","title":"A3-108 Machine Translation System for {L}o{R}es{MT} 2019","authors":["Yadav, Saumitra","Mujadia, Vandan","Shrivastava, Manish"],"emails":["","","m.shrivastava@iiit.ac.in"],"author_id":["saumitra-yadav","vandan-mujadia","manish-shrivastava"],"pages":"64--67","url":"https:\/\/www.aclweb.org\/anthology\/W19-6810","publisher":"European Association for Machine Translation","address":"Dublin, Ireland","year":"2019","month":"August","booktitle":"Proceedings of the 2nd Workshop on Technologies for MT of Low Resource Languages"},{"id":"W19-6811","title":"Factored Neural Machine Translation at {L}o{R}es{MT} 2019","authors":["Bandyopadhyay, Saptarashmi"],"emails":["sbandyo20@gmail.com"],"author_id":["saptarashmi-bandyopadhyay"],"pages":"68--71","url":"https:\/\/www.aclweb.org\/anthology\/W19-6811","publisher":"European Association for Machine Translation","address":"Dublin, Ireland","year":"2019","month":"August","booktitle":"Proceedings of the 2nd Workshop on Technologies for MT of Low Resource Languages"},{"id":"W19-6812","title":"{JHU} {L}o{R}es{MT} 2019 Shared Task System Description","authors":["McNamee, Paul"],"emails":["mcnamee@jhu.edu"],"author_id":["paul-mcnamee"],"pages":"72--75","url":"https:\/\/www.aclweb.org\/anthology\/W19-6812","publisher":"European Association for Machine Translation","address":"Dublin, Ireland","year":"2019","month":"August","booktitle":"Proceedings of the 2nd Workshop on Technologies for MT of Low Resource Languages"}]